MANIFEST.in
README.rst
setup.py
docs/HISTORY.txt
docs/LICENSE.GPL
docs/LICENSE.txt
sentry_regressions/__init__.py
sentry_regressions/plugin.py
sentry_regressions.egg-info/PKG-INFO
sentry_regressions.egg-info/SOURCES.txt
sentry_regressions.egg-info/dependency_links.txt
sentry_regressions.egg-info/entry_points.txt
sentry_regressions.egg-info/not-zip-safe
sentry_regressions.egg-info/requires.txt
sentry_regressions.egg-info/top_level.txt
sentry_regressions/tests/__init__.py
sentry_regressions/tests/test_plugin.py