Metadata-Version: 1.1
Name: sentry-regressions
Version: 1.0.0
Summary: Sentry Plugin to better control regression handling
Home-page: https://github.com/4teamwork/sentry-regressions
Author: 4teamwork AG
Author-email: mailto:info@4teamwork.ch
License: GPL2
Keywords: Sentry Regressions Plugin
Platform: UNKNOWN
Classifier: License :: OSI Approved :: GNU General Public License (GPL)
Classifier: Programming Language :: Python
Classifier: Programming Language :: Python :: 2.7
Classifier: Intended Audience :: Developers
Classifier: Topic :: Software Development :: Libraries :: Python Modules
